
{
  "header": {
    "reportVersion": 1,
    "event": "Allocation failed - JavaScript heap out of memory",
    "trigger": "FatalError",
    "filename": "report.20200520.011618.2600.0.001.json",
    "dumpEventTime": "2020-05-20T01:16:18Z",
    "dumpEventTimeStamp": "1589955378017",
    "processId": 2600,
    "cwd": "C:\\Users\\damia\\OneDrive - Instituto Politecnico Nacional\\Documents\\Escuela\\Unidades de aprendizaje\\Teoría de comunicaciones y señales\\Segundo parcial\\Prácticas\\Práctica 2\\convolution-algorithms",
    "commandLine": [
      "node",
      "C:\\Users\\damia\\OneDrive - Instituto Politecnico Nacional\\Documents\\Escuela\\Unidades de aprendizaje\\Teoría de comunicaciones y señales\\Segundo parcial\\Prácticas\\Práctica 2\\convolution-algorithms\\node_modules\\react-scripts\\scripts\\start.js"
    ],
    "nodejsVersion": "v12.14.1",
    "wordSize": 64,
    "arch": "x64",
    "platform": "win32",
    "componentVersions": {
      "node": "12.14.1",
      "v8": "7.7.299.13-node.16",
      "uv": "1.33.1",
      "zlib": "1.2.11",
      "brotli": "1.0.7",
      "ares": "1.15.0",
      "modules": "72",
      "nghttp2": "1.40.0",
      "napi": "5",
      "llhttp": "2.0.1",
      "http_parser": "2.8.0",
      "openssl": "1.1.1d",
      "cldr": "35.1",
      "icu": "64.2",
      "tz": "2019c",
      "unicode": "12.1"
    },
    "release": {
      "name": "node",
      "lts": "Erbium",
      "headersUrl": "https://nodejs.org/download/release/v12.14.1/node-v12.14.1-headers.tar.gz",
      "sourceUrl": "https://nodejs.org/download/release/v12.14.1/node-v12.14.1.tar.gz",
      "libUrl": "https://nodejs.org/download/release/v12.14.1/win-x64/node.lib"
    },
    "osName": "Windows_NT",
    "osRelease": "10.0.18363",
    "osVersion": "Windows 10 Pro",
    "osMachine": "x86_64",
    "cpus": [
      {
        "model": "AMD Ryzen 7 2700X Eight-Core Processor         ",
        "speed": 3693,
        "user": 829515,
        "nice": 0,
        "sys": 1157156,
        "idle": 21523218,
        "irq": 223062
      },
      {
        "model": "AMD Ryzen 7 2700X Eight-Core Processor         ",
        "speed": 3693,
        "user": 624531,
        "nice": 0,
        "sys": 182562,
        "idle": 22702562,
        "irq": 16265
      },
      {
        "model": "AMD Ryzen 7 2700X Eight-Core Processor         ",
        "speed": 3693,
        "user": 1714796,
        "nice": 0,
        "sys": 746953,
        "idle": 21047906,
        "irq": 8234
      },
      {
        "model": "AMD Ryzen 7 2700X Eight-Core Processor         ",
        "speed": 3693,
        "user": 356828,
        "nice": 0,
        "sys": 100640,
        "idle": 23052187,
        "irq": 1343
      },
      {
        "model": "AMD Ryzen 7 2700X Eight-Core Processor         ",
        "speed": 3693,
        "user": 838718,
        "nice": 0,
        "sys": 345015,
        "idle": 22325921,
        "irq": 4406
      },
      {
        "model": "AMD Ryzen 7 2700X Eight-Core Processor         ",
        "speed": 3693,
        "user": 1199734,
        "nice": 0,
        "sys": 995500,
        "idle": 21314421,
        "irq": 1687
      },
      {
        "model": "AMD Ryzen 7 2700X Eight-Core Processor         ",
        "speed": 3693,
        "user": 987453,
        "nice": 0,
        "sys": 516171,
        "idle": 22006031,
        "irq": 3734
      },
      {
        "model": "AMD Ryzen 7 2700X Eight-Core Processor         ",
        "speed": 3693,
        "user": 242765,
        "nice": 0,
        "sys": 168421,
        "idle": 23098468,
        "irq": 1109
      },
      {
        "model": "AMD Ryzen 7 2700X Eight-Core Processor         ",
        "speed": 3693,
        "user": 688906,
        "nice": 0,
        "sys": 351937,
        "idle": 22468812,
        "irq": 4812
      },
      {
        "model": "AMD Ryzen 7 2700X Eight-Core Processor         ",
        "speed": 3693,
        "user": 109265,
        "nice": 0,
        "sys": 68000,
        "idle": 23332375,
        "irq": 1515
      },
      {
        "model": "AMD Ryzen 7 2700X Eight-Core Processor         ",
        "speed": 3693,
        "user": 819312,
        "nice": 0,
        "sys": 392140,
        "idle": 22298187,
        "irq": 4953
      },
      {
        "model": "AMD Ryzen 7 2700X Eight-Core Processor         ",
        "speed": 3693,
        "user": 104515,
        "nice": 0,
        "sys": 58312,
        "idle": 23346812,
        "irq": 1125
      },
      {
        "model": "AMD Ryzen 7 2700X Eight-Core Processor         ",
        "speed": 3693,
        "user": 573828,
        "nice": 0,
        "sys": 220140,
        "idle": 22715671,
        "irq": 4656
      },
      {
        "model": "AMD Ryzen 7 2700X Eight-Core Processor         ",
        "speed": 3693,
        "user": 140812,
        "nice": 0,
        "sys": 109000,
        "idle": 23259828,
        "irq": 1109
      },
      {
        "model": "AMD Ryzen 7 2700X Eight-Core Processor         ",
        "speed": 3693,
        "user": 561109,
        "nice": 0,
        "sys": 233796,
        "idle": 22714734,
        "irq": 2546
      },
      {
        "model": "AMD Ryzen 7 2700X Eight-Core Processor         ",
        "speed": 3693,
        "user": 471515,
        "nice": 0,
        "sys": 371593,
        "idle": 22666531,
        "irq": 2234
      }
    ],
    "networkInterfaces": [
      {
        "name": "Conexión de área local",
        "internal": false,
        "mac": "00:ff:9a:f7:81:ba",
        "address": "fe80::68e6:4e24:7143:7490",
        "netmask": "ffff:ffff:ffff:ffff::",
        "family": "IPv6",
        "scopeid": 13
      },
      {
        "name": "Conexión de área local",
        "internal": false,
        "mac": "00:ff:9a:f7:81:ba",
        "address": "10.8.0.125",
        "netmask": "255.255.0.0",
        "family": "IPv4"
      },
      {
        "name": "Wi-Fi 5",
        "internal": false,
        "mac": "34:e8:94:f4:83:42",
        "address": "fe80::a095:8bb8:a70d:7009",
        "netmask": "ffff:ffff:ffff:ffff::",
        "family": "IPv6",
        "scopeid": 15
      },
      {
        "name": "Wi-Fi 5",
        "internal": false,
        "mac": "34:e8:94:f4:83:42",
        "address": "192.168.1.76",
        "netmask": "255.255.255.0",
        "family": "IPv4"
      },
      {
        "name": "Loopback Pseudo-Interface 1",
        "internal": true,
        "mac": "00:00:00:00:00:00",
        "address": "::1",
        "netmask": "ffff:ffff:ffff:ffff:ffff:ffff:ffff:ffff",
        "family": "IPv6",
        "scopeid": 0
      },
      {
        "name": "Loopback Pseudo-Interface 1",
        "internal": true,
        "mac": "00:00:00:00:00:00",
        "address": "127.0.0.1",
        "netmask": "255.0.0.0",
        "family": "IPv4"
      }
    ],
    "host": "Damian"
  },
  "javascriptStack": {
    "message": "No stack.",
    "stack": [
      "Unavailable."
    ]
  },
  "nativeStack": [
    {
      "pc": "0x00007ff608b31759",
      "symbol": "std::basic_ostream<char,std::char_traits<char> >::operator<<+10873"
    },
    {
      "pc": "0x00007ff608b35b7c",
      "symbol": "std::basic_ostream<char,std::char_traits<char> >::operator<<+28316"
    },
    {
      "pc": "0x00007ff608b34b38",
      "symbol": "std::basic_ostream<char,std::char_traits<char> >::operator<<+24152"
    },
    {
      "pc": "0x00007ff608c2433b",
      "symbol": "v8::base::CPU::has_sse+37723"
    },
    {
      "pc": "0x00007ff609428c5e",
      "symbol": "v8::Isolate::ReportExternalAllocationLimitReached+94"
    },
    {
      "pc": "0x00007ff609410ca1",
      "symbol": "v8::SharedArrayBuffer::Externalize+833"
    },
    {
      "pc": "0x00007ff6092de56c",
      "symbol": "v8::internal::Heap::EphemeronKeyWriteBarrierFromCode+1436"
    },
    {
      "pc": "0x00007ff6092e9910",
      "symbol": "v8::internal::Heap::ProtectUnprotectedMemoryChunks+1312"
    },
    {
      "pc": "0x00007ff6092e6444",
      "symbol": "v8::internal::Heap::PageFlagsAreConsistent+3204"
    },
    {
      "pc": "0x00007ff6092dbcd3",
      "symbol": "v8::internal::Heap::CollectGarbage+1283"
    },
    {
      "pc": "0x00007ff6092da4a4",
      "symbol": "v8::internal::Heap::AddRetainedMap+2356"
    },
    {
      "pc": "0x00007ff6092fb775",
      "symbol": "v8::internal::Factory::NewFillerObject+53"
    },
    {
      "pc": "0x00007ff609067a49",
      "symbol": "v8::internal::interpreter::JumpTableTargetOffsets::iterator::operator=+4057"
    },
    {
      "pc": "0x00007ff60985463d",
      "symbol": "v8::internal::SetupIsolateDelegate::SetupHeap+567949"
    },
    {
      "pc": "0x00007ff60985642b",
      "symbol": "v8::internal::SetupIsolateDelegate::SetupHeap+575611"
    },
    {
      "pc": "0x00007ff60988fe67",
      "symbol": "v8::internal::SetupIsolateDelegate::SetupHeap+811703"
    },
    {
      "pc": "0x00007ff6098411e5",
      "symbol": "v8::internal::SetupIsolateDelegate::SetupHeap+489013"
    },
    {
      "pc": "0x0000025d67c0fc0f",
      "symbol": ""
    }
  ],
  "javascriptHeap": {
    "totalMemory": 2172473344,
    "totalCommittedMemory": 2172473344,
    "usedMemory": 2136688544,
    "availableMemory": 54298944,
    "memoryLimit": 2197815296,
    "heapSpaces": {
      "read_only_space": {
        "memorySize": 262144,
        "committedMemory": 262144,
        "capacity": 261872,
        "used": 32296,
        "available": 229576
      },
      "new_space": {
        "memorySize": 9437184,
        "committedMemory": 9437184,
        "capacity": 4713696,
        "used": 1048024,
        "available": 3665672
      },
      "old_space": {
        "memorySize": 2088349696,
        "committedMemory": 2088349696,
        "capacity": 2082913856,
        "used": 2062565808,
        "available": 20348048
      },
      "code_space": {
        "memorySize": 1998848,
        "committedMemory": 1998848,
        "capacity": 1608064,
        "used": 1608064,
        "available": 0
      },
      "map_space": {
        "memorySize": 3411968,
        "committedMemory": 3411968,
        "capacity": 2612960,
        "used": 2612960,
        "available": 0
      },
      "large_object_space": {
        "memorySize": 68390912,
        "committedMemory": 68390912,
        "capacity": 68270992,
        "used": 68270992,
        "available": 0
      },
      "code_large_object_space": {
        "memorySize": 622592,
        "committedMemory": 622592,
        "capacity": 550400,
        "used": 550400,
        "available": 0
      },
      "new_large_object_space": {
        "memorySize": 0,
        "committedMemory": 0,
        "capacity": 4713696,
        "used": 0,
        "available": 4713696
      }
    }
  },
  "resourceUsage": {
    "userCpuSeconds": 68.859,
    "kernelCpuSeconds": 3.812,
    "cpuConsumptionPercent": 242.237,
    "maxRss": 2281869312,
    "pageFaults": {
      "IORequired": 777130,
      "IONotRequired": 0
    },
    "fsActivity": {
      "reads": 5807,
      "writes": 6
    }
  },
  "libuv": [
  ],
  "environmentVariables": {
    "ALLUSERSPROFILE": "C:\\ProgramData",
    "APPDATA": "C:\\Users\\damia\\AppData\\Roaming",
    "BABEL_ENV": "development",
    "ChocolateyInstall": "C:\\ProgramData\\chocolatey",
    "ChocolateyLastPathUpdate": "132252607179872782",
    "COLORTERM": "truecolor",
    "CommonProgramFiles": "C:\\Program Files\\Common Files",
    "CommonProgramFiles(x86)": "C:\\Program Files (x86)\\Common Files",
    "CommonProgramW6432": "C:\\Program Files\\Common Files",
    "COMPUTERNAME": "DAMIAN",
    "ComSpec": "C:\\Windows\\system32\\cmd.exe",
    "dp0": "C:\\Users\\damia\\OneDrive - Instituto Politecnico Nacional\\Documents\\Escuela\\Unidades de aprendizaje\\Teoría de comunicaciones y señales\\Segundo parcial\\Prácticas\\Práctica 2\\convolution-algorithms\\node_modules\\.bin\\",
    "DriverData": "C:\\Windows\\System32\\Drivers\\DriverData",
    "FPS_BROWSER_APP_PROFILE_STRING": "Internet Explorer",
    "FPS_BROWSER_USER_PROFILE_STRING": "Default",
    "HOME": "C:\\Users\\damia",
    "HOMEDRIVE": "C:",
    "HOMEPATH": "\\Users\\damia",
    "INIT_CWD": "C:\\Users\\damia\\OneDrive - Instituto Politecnico Nacional\\Documents\\Escuela\\Unidades de aprendizaje\\Teoría de comunicaciones y señales\\Segundo parcial\\Prácticas\\Práctica 2\\convolution-algorithms",
    "LANG": "es_419.UTF-8",
    "LOCALAPPDATA": "C:\\Users\\damia\\AppData\\Local",
    "LOGONSERVER": "\\\\DAMIAN",
    "NODE": "C:\\Program Files\\nodejs\\node.exe",
    "NODE_ENV": "development",
    "NODE_EXE": "C:\\Program Files\\nodejs\\\\node.exe",
    "NODE_PATH": "",
    "NPM_CLI_JS": "C:\\Program Files\\nodejs\\\\node_modules\\npm\\bin\\npm-cli.js",
    "npm_config_access": "",
    "npm_config_allow_same_version": "",
    "npm_config_also": "",
    "npm_config_always_auth": "",
    "npm_config_argv": "{\"remain\":[],\"cooked\":[\"start\"],\"original\":[\"start\"]}",
    "npm_config_audit": "true",
    "npm_config_audit_level": "low",
    "npm_config_auth_type": "legacy",
    "npm_config_before": "",
    "npm_config_bin_links": "true",
    "npm_config_browser": "",
    "npm_config_ca": "",
    "npm_config_cache": "C:\\Users\\damia\\AppData\\Roaming\\npm-cache",
    "npm_config_cache_lock_retries": "10",
    "npm_config_cache_lock_stale": "60000",
    "npm_config_cache_lock_wait": "10000",
    "npm_config_cache_max": "Infinity",
    "npm_config_cache_min": "10",
    "npm_config_cafile": "",
    "npm_config_cert": "",
    "npm_config_cidr": "",
    "npm_config_color": "true",
    "npm_config_commit_hooks": "true",
    "npm_config_depth": "Infinity",
    "npm_config_description": "true",
    "npm_config_dev": "",
    "npm_config_dry_run": "",
    "npm_config_editor": "notepad.exe",
    "npm_config_engine_strict": "",
    "npm_config_fetch_retries": "2",
    "npm_config_fetch_retry_factor": "10",
    "npm_config_fetch_retry_maxtimeout": "60000",
    "npm_config_fetch_retry_mintimeout": "10000",
    "npm_config_force": "",
    "npm_config_format_package_lock": "true",
    "npm_config_fund": "true",
    "npm_config_git": "git",
    "npm_config_git_tag_version": "true",
    "npm_config_global": "",
    "npm_config_globalconfig": "C:\\Users\\damia\\AppData\\Roaming\\npm\\etc\\npmrc",
    "npm_config_globalignorefile": "C:\\Users\\damia\\AppData\\Roaming\\npm\\etc\\npmignore",
    "npm_config_global_style": "",
    "npm_config_group": "",
    "npm_config_ham_it_up": "",
    "npm_config_heading": "npm",
    "npm_config_https_proxy": "",
    "npm_config_if_present": "",
    "npm_config_ignore_prepublish": "",
    "npm_config_ignore_scripts": "",
    "npm_config_init_author_email": "",
    "npm_config_init_author_name": "",
    "npm_config_init_author_url": "",
    "npm_config_init_license": "ISC",
    "npm_config_init_module": "C:\\Users\\damia\\.npm-init.js",
    "npm_config_init_version": "1.0.0",
    "npm_config_json": "",
    "npm_config_key": "",
    "npm_config_legacy_bundling": "",
    "npm_config_link": "",
    "npm_config_local_address": "",
    "npm_config_loglevel": "notice",
    "npm_config_logs_max": "10",
    "npm_config_long": "",
    "npm_config_maxsockets": "50",
    "npm_config_message": "%s",
    "npm_config_metrics_registry": "https://registry.npmjs.org/",
    "npm_config_node_gyp": "C:\\Program Files\\nodejs\\node_modules\\npm\\node_modules\\node-gyp\\bin\\node-gyp.js",
    "npm_config_node_options": "",
    "npm_config_node_version": "12.14.1",
    "npm_config_noproxy": "",
    "npm_config_offline": "",
    "npm_config_onload_script": "",
    "npm_config_only": "",
    "npm_config_optional": "true",
    "npm_config_otp": "",
    "npm_config_package_lock": "true",
    "npm_config_package_lock_only": "",
    "npm_config_parseable": "",
    "npm_config_prefer_offline": "",
    "npm_config_prefer_online": "",
    "npm_config_prefix": "C:\\Users\\damia\\AppData\\Roaming\\npm",
    "npm_config_preid": "",
    "npm_config_production": "",
    "npm_config_progress": "true",
    "npm_config_proxy": "",
    "npm_config_read_only": "",
    "npm_config_rebuild_bundle": "true",
    "npm_config_registry": "https://registry.npmjs.org/",
    "npm_config_rollback": "true",
    "npm_config_save": "true",
    "npm_config_save_bundle": "",
    "npm_config_save_dev": "",
    "npm_config_save_exact": "",
    "npm_config_save_optional": "",
    "npm_config_save_prefix": "^",
    "npm_config_save_prod": "",
    "npm_config_scope": "",
    "npm_config_scripts_prepend_node_path": "warn-only",
    "npm_config_script_shell": "",
    "npm_config_searchexclude": "",
    "npm_config_searchlimit": "20",
    "npm_config_searchopts": "",
    "npm_config_searchstaleness": "900",
    "npm_config_send_metrics": "",
    "npm_config_shell": "C:\\Windows\\system32\\cmd.exe",
    "npm_config_shrinkwrap": "true",
    "npm_config_sign_git_commit": "",
    "npm_config_sign_git_tag": "",
    "npm_config_sso_poll_frequency": "500",
    "npm_config_sso_type": "oauth",
    "npm_config_strict_ssl": "true",
    "npm_config_tag": "latest",
    "npm_config_tag_version_prefix": "v",
    "npm_config_timing": "",
    "npm_config_tmp": "C:\\Users\\damia\\AppData\\Local\\Temp",
    "npm_config_umask": "0000",
    "npm_config_unicode": "",
    "npm_config_unsafe_perm": "true",
    "npm_config_update_notifier": "true",
    "npm_config_usage": "",
    "npm_config_user": "",
    "npm_config_userconfig": "C:\\Users\\damia\\.npmrc",
    "npm_config_user_agent": "npm/6.13.4 node/v12.14.1 win32 x64",
    "npm_config_version": "",
    "npm_config_versions": "",
    "npm_config_viewer": "browser",
    "npm_execpath": "C:\\Program Files\\nodejs\\node_modules\\npm\\bin\\npm-cli.js",
    "npm_lifecycle_event": "start",
    "npm_lifecycle_script": "react-scripts start",
    "npm_node_execpath": "C:\\Program Files\\nodejs\\node.exe",
    "npm_package_browserslist_development_0": "last 1 chrome version",
    "npm_package_browserslist_development_1": "last 1 firefox version",
    "npm_package_browserslist_development_2": "last 1 safari version",
    "npm_package_browserslist_production_0": ">0.2%",
    "npm_package_browserslist_production_1": "not dead",
    "npm_package_browserslist_production_2": "not op_mini all",
    "npm_package_dependencies_bootstrap": "^4.5.0",
    "npm_package_dependencies_jquery": "^3.5.1",
    "npm_package_dependencies_plotly_js": "^1.54.1",
    "npm_package_dependencies_popper_js": "^1.16.1",
    "npm_package_dependencies_react": "^16.13.1",
    "npm_package_dependencies_react_dom": "^16.13.1",
    "npm_package_dependencies_react_plotly_js": "^2.4.0",
    "npm_package_dependencies_react_router_dom": "^5.2.0",
    "npm_package_dependencies_react_scripts": "3.4.1",
    "npm_package_dependencies__testing_library_jest_dom": "^4.2.4",
    "npm_package_dependencies__testing_library_react": "^9.5.0",
    "npm_package_dependencies__testing_library_user_event": "^7.2.1",
    "npm_package_description": "This project was bootstrapped with [Create React App](https://github.com/facebook/create-react-app).",
    "npm_package_eslintConfig_extends": "react-app",
    "npm_package_name": "convolution-algorithms",
    "npm_package_private": "true",
    "npm_package_readmeFilename": "README.md",
    "npm_package_scripts_build": "react-scripts build",
    "npm_package_scripts_eject": "react-scripts eject",
    "npm_package_scripts_start": "react-scripts start",
    "npm_package_scripts_test": "react-scripts test",
    "npm_package_version": "0.1.0",
    "NPM_PREFIX_NPM_CLI_JS": "C:\\Users\\damia\\AppData\\Roaming\\npm\\node_modules\\npm\\bin\\npm-cli.js",
    "NUMBER_OF_PROCESSORS": "16",
    "OneDrive": "C:\\Users\\damia\\OneDrive - Instituto Politecnico Nacional",
    "OneDriveCommercial": "C:\\Users\\damia\\OneDrive - Instituto Politecnico Nacional",
    "OneDriveConsumer": "C:\\Users\\damia\\OneDrive",
    "OS": "Windows_NT",
    "Path": "C:\\Program Files\\nodejs\\node_modules\\npm\\node_modules\\npm-lifecycle\\node-gyp-bin;C:\\Users\\damia\\OneDrive - Instituto Politecnico Nacional\\Documents\\Escuela\\Unidades de aprendizaje\\Teoría de comunicaciones y señales\\Segundo parcial\\Prácticas\\Práctica 2\\convolution-algorithms\\node_modules\\.bin;M:\\MinGW\\bin;C:\\Program Files\\PuTTY\\;M:\\Archivos de programa\\xampp\\php;C:\\ProgramData\\ComposerSetup\\bin;C:\\Windows;C:\\Windows\\System32;C:\\Program Files\\nodejs;C:\\Users\\damia\\AppData\\Local\\Microsoft\\WindowsApps;C:\\Users\\damia\\AppData\\Local\\Programs\\Microsoft VS Code\\bin;C:\\Users\\damia\\AppData\\Roaming\\npm;C:\\Users\\damia\\AppData\\Roaming\\Composer\\vendor\\bin;C:\\Program Files\\MySQL\\MySQL Server 8.0\\bin;",
    "PATHEXT": ".COM;.EXE;.BAT;.CMD;.VBS;.VBE;.JSE;.WSF;.WSH;.MSC;.CPL",
    "PROCESSOR_ARCHITECTURE": "AMD64",
    "PROCESSOR_IDENTIFIER": "AMD64 Family 23 Model 8 Stepping 2, AuthenticAMD",
    "PROCESSOR_LEVEL": "23",
    "PROCESSOR_REVISION": "0802",
    "ProgramData": "C:\\ProgramData",
    "ProgramFiles": "C:\\Program Files",
    "ProgramFiles(x86)": "C:\\Program Files (x86)",
    "ProgramW6432": "C:\\Program Files",
    "PROMPT": "$P$G",
    "PSModulePath": "C:\\Users\\damia\\OneDrive - Instituto Politecnico Nacional\\Documents\\WindowsPowerShell\\Modules;C:\\Program Files\\WindowsPowerShell\\Modules;C:\\Windows\\system32\\WindowsPowerShell\\v1.0\\Modules",
    "PUBLIC": "C:\\Users\\Public",
    "SESSIONNAME": "Console",
    "SystemDrive": "C:",
    "SystemRoot": "C:\\Windows",
    "TEMP": "C:\\Users\\damia\\AppData\\Local\\Temp",
    "TERM_PROGRAM": "vscode",
    "TERM_PROGRAM_VERSION": "1.45.1",
    "TMP": "C:\\Users\\damia\\AppData\\Local\\Temp",
    "USERDOMAIN": "DAMIAN",
    "USERDOMAIN_ROAMINGPROFILE": "DAMIAN",
    "USERNAME": "damia",
    "USERPROFILE": "C:\\Users\\damia",
    "WEBPACK_DEV_SERVER": "true",
    "windir": "C:\\Windows",
    "_prog": "node"
  },
  "sharedObjects": [
    "C:\\Program Files\\nodejs\\node.exe",
    "C:\\Windows\\SYSTEM32\\ntdll.dll",
    "C:\\Windows\\System32\\KERNEL32.DLL",
    "C:\\Windows\\System32\\KERNELBASE.dll",
    "C:\\Windows\\System32\\WS2_32.dll",
    "C:\\Windows\\System32\\RPCRT4.dll",
    "C:\\Windows\\SYSTEM32\\dbghelp.dll",
    "C:\\Windows\\System32\\ADVAPI32.dll",
    "C:\\Windows\\System32\\ucrtbase.dll",
    "C:\\Windows\\System32\\msvcrt.dll",
    "C:\\Windows\\System32\\sechost.dll",
    "C:\\Windows\\System32\\USER32.dll",
    "C:\\Windows\\System32\\win32u.dll",
    "C:\\Windows\\System32\\GDI32.dll",
    "C:\\Windows\\System32\\gdi32full.dll",
    "C:\\Windows\\System32\\msvcp_win.dll",
    "C:\\Windows\\System32\\PSAPI.DLL",
    "C:\\Windows\\System32\\CRYPT32.dll",
    "C:\\Windows\\System32\\MSASN1.dll",
    "C:\\Windows\\SYSTEM32\\IPHLPAPI.DLL",
    "C:\\Windows\\SYSTEM32\\USERENV.dll",
    "C:\\Windows\\System32\\bcrypt.dll",
    "C:\\Windows\\System32\\profapi.dll",
    "C:\\Windows\\SYSTEM32\\WINMM.dll",
    "C:\\Windows\\SYSTEM32\\winmmbase.dll",
    "C:\\Windows\\System32\\cfgmgr32.dll",
    "C:\\Windows\\System32\\bcryptPrimitives.dll",
    "C:\\Windows\\System32\\IMM32.DLL",
    "C:\\Windows\\System32\\powrprof.dll",
    "C:\\Windows\\System32\\UMPDC.dll",
    "C:\\Windows\\SYSTEM32\\CRYPTBASE.DLL",
    "C:\\Windows\\system32\\uxtheme.dll",
    "C:\\Windows\\System32\\combase.dll",
    "C:\\Windows\\system32\\mswsock.dll",
    "C:\\Windows\\System32\\kernel.appcore.dll",
    "C:\\Windows\\System32\\NSI.dll",
    "C:\\Windows\\SYSTEM32\\dhcpcsvc6.DLL",
    "C:\\Windows\\SYSTEM32\\dhcpcsvc.DLL",
    "C:\\Windows\\SYSTEM32\\DNSAPI.dll",
    "C:\\Windows\\System32\\rasadhlp.dll",
    "C:\\Windows\\System32\\fwpuclnt.dll",
    "C:\\Windows\\system32\\napinsp.dll",
    "C:\\Windows\\system32\\pnrpnsp.dll",
    "C:\\Windows\\System32\\winrnr.dll",
    "C:\\Windows\\system32\\NLAapi.dll",
    "C:\\Windows\\system32\\wshbth.dll"
  ]
}